tsl/__init__.py
tsl/_logger.py
tsl/config.py
tsl/imports.py
tsl/lazy_loader.py
tsl/typing.py
tsl/data/__init__.py
tsl/data/batch.py
tsl/data/batch_map.py
tsl/data/data.py
tsl/data/imputation_dataset.py
tsl/data/mixin.py
tsl/data/spatiotemporal_dataset.py
tsl/data/synch_mode.py
tsl/data/datamodule/__init__.py
tsl/data/datamodule/spatiotemporal_datamodule.py
tsl/data/datamodule/splitters.py
tsl/data/loader/__init__.py
tsl/data/loader/disjoint_graph_loader.py
tsl/data/loader/static_graph_loader.py
tsl/data/preprocessing/__init__.py
tsl/data/preprocessing/scalers.py
tsl/datasets/__init__.py
tsl/datasets/air_quality.py
tsl/datasets/elergone.py
tsl/datasets/gpvar.py
tsl/datasets/large_st.py
tsl/datasets/metr_la.py
tsl/datasets/mts_benchmarks.py
tsl/datasets/pems_bay.py
tsl/datasets/pems_benchmarks.py
tsl/datasets/pv_us.py
tsl/datasets/synthetic.py
tsl/datasets/prototypes/__init__.py
tsl/datasets/prototypes/casting.py
tsl/datasets/prototypes/dataset.py
tsl/datasets/prototypes/datetime_dataset.py
tsl/datasets/prototypes/mixin.py
tsl/datasets/prototypes/tabular_dataset.py
tsl/engines/__init__.py
tsl/engines/imputer.py
tsl/engines/predictor.py
tsl/experiment/__init__.py
tsl/experiment/experiment.py
tsl/experiment/resolvers.py
tsl/experiment/loggers/__init__.py
tsl/experiment/loggers/neptune_logger.py
tsl/metrics/__init__.py
tsl/metrics/numpy/__init__.py
tsl/metrics/numpy/functional.py
tsl/metrics/torch/__init__.py
tsl/metrics/torch/functional.py
tsl/metrics/torch/metric_base.py
tsl/metrics/torch/metric_wrappers.py
tsl/metrics/torch/metrics.py
tsl/metrics/torch/pinball_loss.py
tsl/nn/__init__.py
tsl/nn/functional.py
tsl/nn/utils.py
tsl/nn/blocks/__init__.py
tsl/nn/blocks/decoders/__init__.py
tsl/nn/blocks/decoders/att_pool.py
tsl/nn/blocks/decoders/gcn_decoder.py
tsl/nn/blocks/decoders/linear_readout.py
tsl/nn/blocks/decoders/mlp_decoder.py
tsl/nn/blocks/decoders/multi_step_mlp_decoder.py
tsl/nn/blocks/encoders/__init__.py
tsl/nn/blocks/encoders/conditional.py
torch_spatiotemporal-0.9.5.dist-info/LICENSE
torch_spatiotemporal-0.9.5.dist-info/METADATA
torch_spatiotemporal-0.9.5.dist-info/WHEEL
torch_spatiotemporal-0.9.5.dist-info/top_level.txt
torch_spatiotemporal-0.9.5.dist-info/RECORD
