Metadata-Version: 2.1
Name: torch_spatiotemporal
Version: 0.9.5
Summary: A PyTorch library for spatiotemporal data processing
Home-page: https://github.com/TorchSpatiotemporal/tsl
Download-URL: https://github.com/TorchSpatiotemporal/tsl/archive/v0.9.5.tar.gz
Author: Andrea Cini, Ivan Marisca
Author-email: andrea.cini@usi.ch, ivan.marisca@usi.ch
License: MIT
Keywords: pytorch,pytorch-geometric,geometric-deep-learning,graph-neural-networks,temporal-graph-networks,spatiotemporal-graph-neural-networks,spatiotemporal-processing,neural-spatiotemporal-forecasting,time-series-analysis,forecasting
Classifier: Development Status :: 4 - Beta
Classifier: Intended Audience :: Developers
Classifier: Intended Audience :: Science/Research
Classifier: Topic :: Scientific/Engineering :: Artificial Intelligence
Classifier: License :: OSI Approved :: MIT License
Classifier: Programming Language :: Python :: 3.8
Classifier: Programming Language :: Python :: 3.9
Classifier: Programming Language :: Python :: 3.10
Classifier: Programming Language :: Python :: 3.11
Requires-Python: >=3.8
License-File: LICENSE
Requires-Dist: einops
Requires-Dist: numpy >1.20.3
Requires-Dist: pandas >=1.4
Requires-Dist: pytorch-lightning >=1.8
Requires-Dist: PyYAML
Requires-Dist: scikit-learn
Requires-Dist: scipy
Requires-Dist: tables
Requires-Dist: torchmetrics >=0.7
Requires-Dist: tqdm
Provides-Extra: doc
Requires-Dist: matplotlib ; extra == 'doc'
Requires-Dist: mpld3 ; extra == 'doc'
Requires-Dist: hydra-core ; extra == 'doc'
Requires-Dist: omegaconf ; extra == 'doc'
Requires-Dist: holidays ; extra == 'doc'
Requires-Dist: neptune-client >=0.14 ; extra == 'doc'
Requires-Dist: docutils ; extra == 'doc'
Requires-Dist: sphinx ; extra == 'doc'
Requires-Dist: sphinx-design ; extra == 'doc'
Requires-Dist: sphinx-copybutton ; extra == 'doc'
Requires-Dist: sphinxext-opengraph ; extra == 'doc'
Requires-Dist: sphinx-hoverxref ; extra == 'doc'
Requires-Dist: myst-nb ; extra == 'doc'
Requires-Dist: furo ; extra == 'doc'
Provides-Extra: experiment
Requires-Dist: hydra-core ; extra == 'experiment'
Requires-Dist: omegaconf ; extra == 'experiment'
Provides-Extra: full
Requires-Dist: matplotlib ; extra == 'full'
Requires-Dist: mpld3 ; extra == 'full'
Requires-Dist: hydra-core ; extra == 'full'
Requires-Dist: omegaconf ; extra == 'full'
Requires-Dist: holidays ; extra == 'full'
Requires-Dist: neptune-client >=0.14 ; extra == 'full'
